pqcat/__init__.py
pqcat/_version.py
pqcat/main.py
pqcat/py.typed
pqcat-0.0.5.dist-info/METADATA
pqcat-0.0.5.dist-info/WHEEL
pqcat-0.0.5.dist-info/entry_points.txt
pqcat-0.0.5.dist-info/licenses/LICENSE
pqcat-0.0.5.dist-info/RECORD
