Metadata-Version: 2.4
Name: pqcat
Version: 0.0.5
Summary: pqcat is a fast command-line tool for inspecting Parquet files
Project-URL: Homepage, https://github.com/speed1313/pqcat
Author-email: speed1313 <speedtry13@icloud.com>
License-Expression: Apache-2.0
License-File: LICENSE
Requires-Python: >=3.12
Requires-Dist: polars>=1.31.0
Requires-Dist: tabulate>=0.9.0
Requires-Dist: typer>=0.16.0
